{
  "iso": "xemu-perf-tests-v2025-07-12_20-45-10-665226282.iso",
  "suite_allowlist": null,
  "xemu_version": "xemu-0.8.88-master-dcd524c4bc3cfa1459f88e859863c7ee8a3806b1",
  "xemu_machine_info": "xemu_version: 0.8.88\nxemu_branch: master\nxemu_commit: dcd524c4bc3cfa1459f88e859863c7ee8a3806b1\nxemu_date: Wed Jul  2 08:44:58 UTC 2025\nCPU: Intel(R) Core(TM) i5-4570 CPU @ 3.20GHz\nOS_Version:  22H2\nGL_VENDOR: Intel\nGL_RENDERER: Intel(R) HD Graphics 4600\nGL_VERSION: 4.0.0 - Build 20.19.15.5126\nGL_SHADING_LANGUAGE_VERSION: 4.00 - Build 20.19.15.5126\n         Automatically detecting the format is dangerous for raw images, write operations on block 0 will be restricted.\n         Specify the 'raw' format explicitly to remove the restrictions.\n",
  "machine_info": {
    "cpu_manufacturer": "Intel(R) Core(TM) i5-4570 CPU @ 3.20GHz",
    "cpu_vendor_id": "GenuineIntel",
    "cpu_stepping": 3,
    "cpu_model": 60,
    "cpu_family": 6,
    "cpu_cores": 4,
    "hw_threads": 4,
    "os_system": "Windows",
    "os_release": "10",
    "os_version": "10.0.19045",
    "os_machine_type": "AMD64",
    "cpu_freq_max": 3201.0,
    "os_win_edition": "Education",
    "os_win_version": [
      "10",
      "10.0.19045",
      "SP0",
      "Multiprocessor Free"
    ]
  },
  "renderer": "GL",
  "results": [
    {
      "name": "High vertex count::HighVtxCount-arrays",
      "iterations": 100,
      "total_us": 8002,
      "average_us": 80,
      "min_us": 66,
      "max_us": 1100,
      "raw_results": [
        1100,
        96,
        67,
        68,
        67,
        81,
        80,
        120,
        67,
        67,
        66,
        66,
        66,
        66,
        71,
        67,
        66,
        66,
        66,
        66,
        66,
        76,
        66,
        108,
        68,
        67,
        66,
        66,
        69,
        66,
        66,
        66,
        66,
        80,
        68,
        94,
        66,
        66,
        67,
        66,
        66,
        66,
        66,
        71,
        66,
        66,
        66,
        67,
        66,
        76,
        66,
        66,
        66,
        66,
        66,
        66,
        66,
        69,
        66,
        66,
        66,
        66,
        83,
        83,
        67,
        66,
        66,
        66,
        66,
        66,
        66,
        66,
        68,
        66,
        66,
        66,
        80,
        72,
        110,
        69,
        66,
        66,
        66,
        66,
        66,
        66,
        69,
        66,
        66,
        66,
        66,
        66,
        77,
        66,
        66,
        67,
        66,
        67,
        67,
        66
      ]
    },
    {
      "name": "High vertex count::HighVtxCount-inlinearrays",
      "iterations": 10,
      "total_us": 1361443,
      "average_us": 136144,
      "min_us": 106081,
      "max_us": 187667,
      "raw_results": [
        185554,
        161838,
        121264,
        187667,
        148654,
        121015,
        106081,
        106132,
        112067,
        111171
      ]
    },
    {
      "name": "High vertex count::HighVtxCount-inlinebuffers",
      "iterations": 5,
      "total_us": 2683944,
      "average_us": 536788,
      "min_us": 497508,
      "max_us": 634480,
      "raw_results": [
        634480,
        519741,
        513749,
        518466,
        497508
      ]
    },
    {
      "name": "High vertex count::HighVtxCount-inlineelements",
      "iterations": 50,
      "total_us": 284094,
      "average_us": 5681,
      "min_us": 4724,
      "max_us": 8765,
      "raw_results": [
        5339,
        4793,
        7130,
        4960,
        5147,
        8765,
        5015,
        7428,
        6140,
        4724,
        6021,
        5439,
        4909,
        6383,
        5352,
        5716,
        7966,
        5215,
        5135,
        6540,
        5110,
        5114,
        6931,
        5084,
        4939,
        6659,
        5674,
        4845,
        5788,
        4866,
        4804,
        6659,
        5698,
        4845,
        5863,
        5508,
        4954,
        6858,
        5793,
        4810,
        5881,
        5473,
        4878,
        6771,
        5040,
        4852,
        6761,
        5012,
        4782,
        5725
      ]
    },
    {
      "name": "Vertex buffer allocation::MixedVtxAlloc-arrays",
      "iterations": 10,
      "total_us": 3748365,
      "average_us": 374836,
      "min_us": 337845,
      "max_us": 444582,
      "raw_results": [
        376161,
        361422,
        371431,
        373227,
        337845,
        345397,
        390255,
        409424,
        338621,
        444582
      ]
    },
    {
      "name": "Vertex buffer allocation::MixedVtxAlloc-inlinearrays",
      "iterations": 10,
      "total_us": 2753726,
      "average_us": 275372,
      "min_us": 187019,
      "max_us": 626875,
      "raw_results": [
        290492,
        207305,
        199557,
        187019,
        234910,
        356633,
        221812,
        215976,
        213147,
        626875
      ]
    },
    {
      "name": "Vertex buffer allocation::MixedVtxAlloc-inlinebuffers",
      "iterations": 10,
      "total_us": 11415829,
      "average_us": 1141582,
      "min_us": 1086562,
      "max_us": 1261264,
      "raw_results": [
        1249812,
        1261264,
        1117806,
        1086562,
        1106961,
        1095139,
        1127210,
        1087270,
        1179360,
        1104445
      ]
    },
    {
      "name": "Vertex buffer allocation::MixedVtxAlloc-inlineelements",
      "iterations": 10,
      "total_us": 534289,
      "average_us": 53428,
      "min_us": 50688,
      "max_us": 56721,
      "raw_results": [
        54925,
        55525,
        55576,
        52109,
        51146,
        54925,
        56721,
        51136,
        51538,
        50688
      ]
    },
    {
      "name": "Vertex buffer allocation::TinyAlloc-arrays",
      "iterations": 10,
      "total_us": 568149,
      "average_us": 56814,
      "min_us": 54676,
      "max_us": 58382,
      "raw_results": [
        57479,
        58382,
        55318,
        54676,
        57507,
        55377,
        56866,
        56111,
        58204,
        58229
      ]
    },
    {
      "name": "Vertex buffer allocation::TinyAlloc-inlinearrays",
      "iterations": 10,
      "total_us": 2462353,
      "average_us": 246235,
      "min_us": 219187,
      "max_us": 283735,
      "raw_results": [
        283735,
        237939,
        256835,
        279510,
        219187,
        224626,
        220461,
        279843,
        233938,
        226279
      ]
    },
    {
      "name": "Vertex buffer allocation::TinyAlloc-inlinebuffers",
      "iterations": 10,
      "total_us": 1346433,
      "average_us": 134643,
      "min_us": 122241,
      "max_us": 201102,
      "raw_results": [
        128614,
        139352,
        201102,
        131159,
        122546,
        123546,
        124568,
        124713,
        122241,
        128592
      ]
    },
    {
      "name": "Vertex buffer allocation::TinyAlloc-inlineelements",
      "iterations": 10,
      "total_us": 566701,
      "average_us": 56670,
      "min_us": 54647,
      "max_us": 59667,
      "raw_results": [
        59006,
        59667,
        56958,
        57157,
        55262,
        55379,
        58443,
        55121,
        54647,
        55061
      ]
    }
  ],
  "xemu_tag": "v0.8.88"
}