{
  "iso": "xemu-perf-tests-v2025-07-12_20-45-10-665226282.iso",
  "suite_allowlist": null,
  "xemu_version": "xemu-0.8.88-master-dcd524c4bc3cfa1459f88e859863c7ee8a3806b1",
  "xemu_machine_info": "xemu_version: 0.8.88\nxemu_branch: master\nxemu_commit: dcd524c4bc3cfa1459f88e859863c7ee8a3806b1\nxemu_date: Wed Jul  2 08:44:58 UTC 2025\nCPU: 12th Gen Intel(R) Core(TM) i5-12500\nOS_Version:  24H2\nGL_VENDOR: Intel\nGL_RENDERER: Intel(R) UHD Graphics 770\nGL_VERSION: 4.0.0 - Build 32.0.101.6881\nGL_SHADING_LANGUAGE_VERSION: 4.00 - Build 32.0.101.6881\n         Automatically detecting the format is dangerous for raw images, write operations on block 0 will be restricted.\n         Specify the 'raw' format explicitly to remove the restrictions.\nEnabled instance extensions:\n- VK_KHR_surface\n- VK_KHR_win32_surface\n- VK_KHR_get_physical_device_properties2\n- VK_KHR_external_semaphore_capabilities\n- VK_KHR_external_memory_capabilities\nAvailable physical devices:\n- Intel(R) UHD Graphics 770\nSelected physical device: Intel(R) UHD Graphics 770\n- Vendor: 8086, Device: 4690\n- Driver Version: 0.405.2785\nEnabled device extensions:\n- VK_KHR_external_semaphore\n- VK_KHR_external_memory\n- VK_KHR_external_memory_win32\n- VK_KHR_external_semaphore_win32\n- VK_EXT_custom_border_color\n- VK_EXT_provoking_vertex\n- VK_EXT_memory_budget\n",
  "machine_info": {
    "cpu_manufacturer": "12th Gen Intel(R) Core(TM) i5-12500",
    "cpu_vendor_id": "GenuineIntel",
    "cpu_stepping": 5,
    "cpu_model": 151,
    "cpu_family": 6,
    "cpu_cores": 6,
    "hw_threads": 12,
    "os_system": "Windows",
    "os_release": "10",
    "os_version": "10.0.26100",
    "os_machine_type": "AMD64",
    "cpu_freq_max": 3000.0,
    "os_win_edition": "Education",
    "os_win_version": [
      "10",
      "10.0.26100",
      "SP0",
      "Multiprocessor Free"
    ]
  },
  "renderer": "VK",
  "results": [
    {
      "name": "High vertex count::HighVtxCount-arrays",
      "iterations": 100,
      "total_us": 3992,
      "average_us": 39,
      "min_us": 29,
      "max_us": 870,
      "raw_results": [
        870,
        55,
        31,
        31,
        29,
        30,
        30,
        29,
        29,
        30,
        43,
        30,
        31,
        37,
        42,
        39,
        31,
        29,
        30,
        30,
        30,
        30,
        30,
        30,
        30,
        30,
        30,
        29,
        30,
        30,
        32,
        31,
        29,
        30,
        30,
        30,
        30,
        30,
        31,
        30,
        29,
        61,
        30,
        30,
        40,
        31,
        29,
        30,
        30,
        30,
        30,
        29,
        30,
        30,
        29,
        30,
        30,
        30,
        30,
        30,
        30,
        33,
        30,
        30,
        29,
        30,
        30,
        30,
        30,
        30,
        29,
        30,
        30,
        56,
        30,
        32,
        39,
        29,
        37,
        30,
        29,
        30,
        30,
        29,
        30,
        30,
        33,
        30,
        30,
        29,
        29,
        36,
        31,
        29,
        29,
        30,
        29,
        29,
        30,
        30
      ]
    },
    {
      "name": "High vertex count::HighVtxCount-inlinearrays",
      "iterations": 10,
      "total_us": 529108,
      "average_us": 52910,
      "min_us": 50583,
      "max_us": 61045,
      "raw_results": [
        53082,
        61045,
        50765,
        53220,
        50583,
        50891,
        52525,
        51414,
        54051,
        51532
      ]
    },
    {
      "name": "High vertex count::HighVtxCount-inlinebuffers",
      "iterations": 5,
      "total_us": 1205718,
      "average_us": 241143,
      "min_us": 239792,
      "max_us": 242775,
      "raw_results": [
        239792,
        242775,
        240202,
        241167,
        241782
      ]
    },
    {
      "name": "High vertex count::HighVtxCount-inlineelements",
      "iterations": 50,
      "total_us": 172004,
      "average_us": 3440,
      "min_us": 2315,
      "max_us": 7264,
      "raw_results": [
        2315,
        2719,
        2735,
        3111,
        2692,
        5550,
        2988,
        3756,
        4627,
        5365,
        3730,
        4133,
        3171,
        5765,
        2609,
        2550,
        2884,
        5394,
        4841,
        2853,
        3446,
        4540,
        3616,
        2852,
        2600,
        2459,
        3669,
        5068,
        2786,
        2468,
        2493,
        2811,
        3074,
        7264,
        3727,
        2785,
        3135,
        2838,
        2474,
        2487,
        2504,
        2844,
        2784,
        3471,
        2510,
        2642,
        4189,
        5101,
        3112,
        2467
      ]
    },
    {
      "name": "Vertex buffer allocation::MixedVtxAlloc-arrays",
      "iterations": 10,
      "total_us": 1434514,
      "average_us": 143451,
      "min_us": 137262,
      "max_us": 150372,
      "raw_results": [
        148423,
        150372,
        143530,
        150093,
        139407,
        144811,
        138757,
        137262,
        142512,
        139347
      ]
    },
    {
      "name": "Vertex buffer allocation::MixedVtxAlloc-inlinearrays",
      "iterations": 10,
      "total_us": 874663,
      "average_us": 87466,
      "min_us": 84168,
      "max_us": 90311,
      "raw_results": [
        90311,
        85416,
        87580,
        86488,
        87096,
        86789,
        89994,
        86730,
        84168,
        90091
      ]
    },
    {
      "name": "Vertex buffer allocation::MixedVtxAlloc-inlinebuffers",
      "iterations": 10,
      "total_us": 5053819,
      "average_us": 505381,
      "min_us": 491842,
      "max_us": 586750,
      "raw_results": [
        494156,
        493977,
        492022,
        492303,
        503645,
        491842,
        493138,
        497253,
        508733,
        586750
      ]
    },
    {
      "name": "Vertex buffer allocation::MixedVtxAlloc-inlineelements",
      "iterations": 10,
      "total_us": 339051,
      "average_us": 33905,
      "min_us": 30760,
      "max_us": 39062,
      "raw_results": [
        39062,
        31104,
        31075,
        33273,
        35780,
        32736,
        30760,
        34939,
        37568,
        32754
      ]
    },
    {
      "name": "Vertex buffer allocation::TinyAlloc-arrays",
      "iterations": 10,
      "total_us": 578753,
      "average_us": 57875,
      "min_us": 23565,
      "max_us": 137632,
      "raw_results": [
        33701,
        31900,
        29608,
        34897,
        137632,
        45124,
        23565,
        27949,
        89404,
        124973
      ]
    },
    {
      "name": "Vertex buffer allocation::TinyAlloc-inlinearrays",
      "iterations": 10,
      "total_us": 1921293,
      "average_us": 192129,
      "min_us": 164357,
      "max_us": 208535,
      "raw_results": [
        191011,
        192173,
        201479,
        208535,
        192533,
        199222,
        183764,
        164357,
        192389,
        195830
      ]
    },
    {
      "name": "Vertex buffer allocation::TinyAlloc-inlinebuffers",
      "iterations": 10,
      "total_us": 1641235,
      "average_us": 164123,
      "min_us": 150460,
      "max_us": 187260,
      "raw_results": [
        187260,
        150460,
        159928,
        163707,
        154960,
        166818,
        155429,
        168984,
        181511,
        152178
      ]
    },
    {
      "name": "Vertex buffer allocation::TinyAlloc-inlineelements",
      "iterations": 10,
      "total_us": 536266,
      "average_us": 53626,
      "min_us": 22909,
      "max_us": 137424,
      "raw_results": [
        137424,
        83172,
        44843,
        39835,
        59085,
        27684,
        30651,
        22909,
        64042,
        26621
      ]
    }
  ],
  "xemu_tag": "v0.8.88"
}