{
  "iso": "xemu-perf-tests-v2025-07-09_18-34-59-855206728.iso",
  "suite_allowlist": null,
  "xemu_version": "xemu-0.8.69-master-26c451fc36c378976f7dee1431ec279cc7df4515",
  "xemu_machine_info": "xemu_version: 0.8.69\nxemu_branch: master\nxemu_commit: 26c451fc36c378976f7dee1431ec279cc7df4515\nxemu_date: Tue Jun  3 08:59:16 UTC 2025\nCPU: AMD Ryzen 7 5800X 8-Core Processor             \nOS_Version:  22H2\nGL_VENDOR: NVIDIA Corporation\nGL_RENDERER: NVIDIA GeForce RTX 3080/PCIe/SSE2\nGL_VERSION: 4.0.0 NVIDIA 576.88\nGL_SHADING_LANGUAGE_VERSION: 4.00 NVIDIA via Cg compiler\n         Automatically detecting the format is dangerous for raw images, write operations on block 0 will be restricted.\n         Specify the 'raw' format explicitly to remove the restrictions.\n",
  "machine_info": {
    "cpu_manufacturer": "AMD Ryzen 7 5800X 8-Core Processor",
    "cpu_vendor_id": "AuthenticAMD",
    "cpu_stepping": "N/A",
    "cpu_model": 33,
    "cpu_family": 25,
    "cpu_cores": 8,
    "hw_threads": 16,
    "os_system": "Windows",
    "os_release": "10",
    "os_version": "10.0.19045",
    "os_machine_type": "AMD64",
    "cpu_freq_max": 3801.0,
    "os_win_edition": "Education",
    "os_win_version": [
      "10",
      "10.0.19045",
      "SP0",
      "Multiprocessor Free"
    ]
  },
  "renderer": "GL",
  "results": [
    {
      "name": "High vertex count::HighVtxCount-arrays",
      "iterations": 100,
      "total_us": 5141,
      "average_us": 51,
      "min_us": 35,
      "max_us": 1119,
      "raw_results": [
        1119,
        49,
        36,
        37,
        54,
        36,
        36,
        36,
        35,
        36,
        35,
        50,
        39,
        41,
        42,
        37,
        36,
        36,
        36,
        57,
        127,
        52,
        46,
        40,
        35,
        36,
        35,
        39,
        36,
        36,
        35,
        36,
        55,
        36,
        35,
        35,
        38,
        35,
        35,
        36,
        36,
        39,
        36,
        36,
        40,
        38,
        37,
        42,
        39,
        39,
        40,
        38,
        38,
        57,
        50,
        49,
        79,
        46,
        39,
        40,
        38,
        38,
        38,
        37,
        38,
        38,
        38,
        40,
        39,
        38,
        38,
        38,
        38,
        38,
        39,
        38,
        40,
        38,
        38,
        37,
        38,
        45,
        38,
        38,
        38,
        38,
        38,
        38,
        38,
        37,
        37,
        38,
        38,
        38,
        38,
        41,
        42,
        42,
        40,
        38
      ]
    },
    {
      "name": "High vertex count::HighVtxCount-inlinearrays",
      "iterations": 10,
      "total_us": 379623,
      "average_us": 37962,
      "min_us": 37029,
      "max_us": 39732,
      "raw_results": [
        38234,
        38061,
        37717,
        37389,
        38269,
        37029,
        39732,
        37836,
        37216,
        38140
      ]
    },
    {
      "name": "High vertex count::HighVtxCount-inlinebuffers",
      "iterations": 5,
      "total_us": 1117231,
      "average_us": 223446,
      "min_us": 216672,
      "max_us": 231149,
      "raw_results": [
        231149,
        224618,
        226667,
        218125,
        216672
      ]
    },
    {
      "name": "High vertex count::HighVtxCount-inlineelements",
      "iterations": 50,
      "total_us": 134005,
      "average_us": 2680,
      "min_us": 2483,
      "max_us": 4083,
      "raw_results": [
        2887,
        2552,
        2770,
        2681,
        2546,
        4083,
        2901,
        2618,
        2761,
        2811,
        2931,
        3014,
        2592,
        2568,
        2523,
        2571,
        2756,
        2899,
        2579,
        2610,
        2681,
        2656,
        2666,
        3169,
        2608,
        2527,
        2585,
        2743,
        2798,
        2699,
        2582,
        2595,
        2532,
        2516,
        2623,
        2613,
        2605,
        2613,
        2519,
        2487,
        2532,
        2484,
        2557,
        2670,
        2483,
        2589,
        2551,
        2628,
        2498,
        2543
      ]
    },
    {
      "name": "Vertex buffer allocation::MixedVtxAlloc-arrays",
      "iterations": 10,
      "total_us": 1116650,
      "average_us": 111665,
      "min_us": 107743,
      "max_us": 115833,
      "raw_results": [
        111453,
        115833,
        112288,
        114558,
        112375,
        109868,
        107960,
        107743,
        109194,
        115378
      ]
    },
    {
      "name": "Vertex buffer allocation::MixedVtxAlloc-inlinearrays",
      "iterations": 10,
      "total_us": 956450,
      "average_us": 95645,
      "min_us": 90698,
      "max_us": 101115,
      "raw_results": [
        99833,
        93047,
        95193,
        93619,
        92090,
        90698,
        92651,
        98539,
        99665,
        101115
      ]
    },
    {
      "name": "Vertex buffer allocation::MixedVtxAlloc-inlinebuffers",
      "iterations": 10,
      "total_us": 5256902,
      "average_us": 525690,
      "min_us": 515221,
      "max_us": 559095,
      "raw_results": [
        522790,
        559095,
        535371,
        522807,
        528124,
        523743,
        515914,
        515221,
        515732,
        518105
      ]
    },
    {
      "name": "Vertex buffer allocation::MixedVtxAlloc-inlineelements",
      "iterations": 10,
      "total_us": 281592,
      "average_us": 28159,
      "min_us": 27033,
      "max_us": 30142,
      "raw_results": [
        27469,
        30142,
        27783,
        27353,
        27554,
        28261,
        29321,
        29358,
        27033,
        27318
      ]
    },
    {
      "name": "Vertex buffer allocation::TinyAlloc-arrays",
      "iterations": 10,
      "total_us": 271871,
      "average_us": 27187,
      "min_us": 25963,
      "max_us": 28145,
      "raw_results": [
        25963,
        26536,
        27049,
        26959,
        27182,
        28145,
        27674,
        27146,
        27525,
        27692
      ]
    },
    {
      "name": "Vertex buffer allocation::TinyAlloc-inlinearrays",
      "iterations": 10,
      "total_us": 563277,
      "average_us": 56327,
      "min_us": 51575,
      "max_us": 62209,
      "raw_results": [
        62209,
        59704,
        55187,
        57825,
        54493,
        54365,
        57461,
        51575,
        56767,
        53691
      ]
    },
    {
      "name": "Vertex buffer allocation::TinyAlloc-inlinebuffers",
      "iterations": 10,
      "total_us": 511763,
      "average_us": 51176,
      "min_us": 49230,
      "max_us": 53373,
      "raw_results": [
        51849,
        53269,
        50737,
        49230,
        51510,
        52028,
        53373,
        50412,
        49678,
        49677
      ]
    },
    {
      "name": "Vertex buffer allocation::TinyAlloc-inlineelements",
      "iterations": 10,
      "total_us": 280995,
      "average_us": 28099,
      "min_us": 26714,
      "max_us": 29266,
      "raw_results": [
        26714,
        27087,
        28385,
        28002,
        27850,
        27523,
        28893,
        28757,
        29266,
        28518
      ]
    }
  ]
}